BURBERRY.py
DIOR.py
GUCCI.py
HERMES.py
JIMMYCHOO.py
Boutique_crawling-0.0.1.dist-info/METADATA
Boutique_crawling-0.0.1.dist-info/WHEEL
Boutique_crawling-0.0.1.dist-info/top_level.txt
Boutique_crawling-0.0.1.dist-info/RECORD
