Metadata-Version: 2.1
Name: Boutique-crawling
Version: 0.0.1
Summary: Boutique brand web crawling code
Home-page: http://yangjun-ux.github.io
Author: Jun Yang, Daeseon Cho, Jinkyung Oh
Author-email: nov16jun@gmail.com
License: MIT
Platform: UNKNOWN
Requires-Python: >=3
